flex/__init__.py
flex/_version.py
flex/base.py
flex/flex.py
flex/json_encoder.py
flex/static.py
flex/extensions/__init__.py
flex/extensions/bindata.py
flex/extensions/jsondata.py
flex/extensions/tabledata.py
flex_format-0.2.18.dist-info/LICENSE
flex_format-0.2.18.dist-info/METADATA
flex_format-0.2.18.dist-info/WHEEL
flex_format-0.2.18.dist-info/top_level.txt
flex_format-0.2.18.dist-info/RECORD
