Metadata-Version: 2.1
Name: flex-format
Version: 0.2.18
Summary: A flexible file format for astronomical (and other) data
Home-page: https://github.com/AWehrhahn/flex-format
Author: Ansgar Wehrhahn
Author-email: ansgar.wehrhahn@physics.uu.se
License: UNKNOWN
Platform: UNKNOWN
Classifier: Programming Language :: Python :: 3
Classifier: License :: OSI Approved :: MIT License
Classifier: Operating System :: OS Independent
Requires-Python: >=3.6
